agent_chat_api/__init__.py
agent_chat_api/apps.py
agent_chat_api/models.py
agent_chat_api/urls.py
agent_chat_api/views.py
agent_chat_api/services/agent_service.py
agent_chat_api/services/chat_service.py
agent_chat_api/services/letta_client.py
agent_chat_api/services/transcription_service.py
agent_chat_api-0.1.3.dist-info/METADATA
agent_chat_api-0.1.3.dist-info/WHEEL
agent_chat_api-0.1.3.dist-info/top_level.txt
agent_chat_api-0.1.3.dist-info/RECORD
