Metadata-Version: 2.4
Name: agent_chat_api
Version: 0.1.3
Requires-Dist: Django>=5.1.4
Requires-Dist: letta-client>=0.1.223
Requires-Dist: openai==1.95.1
Dynamic: requires-dist
